{
  "timestamp": "2025-08-14T16:12:00+05:30",
  "source": "ambientweather-backfill",
  "outdoor": {
    "temperature": 74.5,
    "feelsLike": 75.41,
    "dewPoint": 67.91,
    "humidity": 80.0
  },
  "wind": {
    "speed": 1.79,
    "gust": 2.24,
    "directionDeg": 253.0
  },
  "rain": {
    "hourly": null,
    "daily": 0.079,
    "weekly": 0.669,
    "monthly": 4.339,
    "yearly": 7.091,
    "total": 7.091
  },
  "pressure": {
    "relative": 29.911,
    "absolute": 27.238
  },
  "solar": {
    "uv": null,
    "radiation": 51.36
  }
}