{
  "timestamp": "2025-10-20T02:49:26.811000+05:30",
  "source": "ambientweather-backfill",
  "outdoor": {
    "temperature": 70.9,
    "feelsLike": 71.83,
    "dewPoint": 67.16,
    "humidity": 88.0
  },
  "wind": {
    "speed": 0.67,
    "gust": 1.12,
    "directionDeg": 189.0
  },
  "rain": {
    "hourly": 0.0,
    "daily": 0.142,
    "weekly": 0.709,
    "monthly": 5.071,
    "yearly": 12.161,
    "total": 12.161
  },
  "pressure": {
    "relative": 29.964,
    "absolute": 27.292
  },
  "solar": {
    "uv": 0.0,
    "radiation": 0.0
  }
}