{
  "timestamp": "2025-10-03T22:30:00",
  "outdoor": {
    "temperature": 71.1,
    "feelsLike": 72.0,
    "dewPoint": 67.03,
    "humidity": 87.0
  },
  "wind": {
    "speed": 1.79,
    "gust": 3.36,
    "maxDailyGust": 17.22,
    "directionDeg": 279.0
  },
  "rain": {
    "hourly": 0.0,
    "daily": 0.339,
    "weekly": 0.5,
    "monthly": 0.5,
    "yearly": 7.591,
    "total": 7.591
  },
  "pressure": {
    "relative": 30.094,
    "absolute": 27.422
  },
  "solar": {
    "uv": 0.0,
    "radiation": 0.0
  },
  "indoor": {
    "temperature": 80.2,
    "humidity": 69.0
  }
}