{
  "timestamp": "2025-09-05T15:30:00",
  "outdoor": {
    "temperature": 83.3,
    "feelsLike": 86.15,
    "dewPoint": 67.45,
    "humidity": 59.0
  },
  "wind": {
    "speed": 2.46,
    "gust": 3.36,
    "maxDailyGust": 9.17,
    "directionDeg": 186.0
  },
  "rain": {
    "hourly": 0.0,
    "daily": 0.0,
    "weekly": 0.043,
    "monthly": 0.043,
    "yearly": 0.043,
    "total": 0.043
  },
  "pressure": {
    "relative": 29.946,
    "absolute": 27.274
  },
  "solar": {
    "uv": 2.0,
    "radiation": 257.22
  },
  "indoor": {
    "temperature": 80.2,
    "humidity": 68.0
  }
}