{
  "timestamp": "2025-09-16T18:19:27.904000+05:30",
  "source": "ambientweather-backfill",
  "outdoor": {
    "temperature": 79.5,
    "feelsLike": 80.3,
    "dewPoint": 67.56,
    "humidity": 67.0
  },
  "wind": {
    "speed": 1.12,
    "gust": 1.12,
    "directionDeg": 247.0
  },
  "rain": {
    "hourly": 0.0,
    "daily": 0.0,
    "weekly": 0,
    "monthly": 3.512,
    "yearly": 3.512,
    "total": 3.512
  },
  "pressure": {
    "relative": 29.958,
    "absolute": 27.286
  },
  "solar": {
    "uv": 0.0,
    "radiation": 0.56
  }
}