{
  "timestamp": "2025-11-17T16:19:26.627000+05:30",
  "source": "ambientweather-backfill",
  "outdoor": {
    "temperature": 78.3,
    "feelsLike": 78.65,
    "dewPoint": 63.25,
    "humidity": 60.0
  },
  "wind": {
    "speed": 2.46,
    "gust": 3.36,
    "directionDeg": 83.0
  },
  "rain": {
    "hourly": 0.0,
    "daily": 0.0,
    "weekly": 0,
    "monthly": 0.0,
    "yearly": 12.642,
    "total": 12.642
  },
  "pressure": {
    "relative": 30.067,
    "absolute": 27.395
  },
  "solar": {
    "uv": 0.0,
    "radiation": 69.16
  }
}