{
  "timestamp": "2025-09-14T05:30:00",
  "outdoor": {
    "temperature": 67.6,
    "feelsLike": 67.6,
    "dewPoint": 63.59,
    "humidity": 87.0
  },
  "wind": {
    "speed": 0.22,
    "gust": 1.12,
    "maxDailyGust": 4.47,
    "directionDeg": 202.0
  },
  "rain": {
    "hourly": 0.0,
    "daily": 0.0,
    "weekly": 1.031,
    "monthly": 3.512,
    "yearly": 3.512,
    "total": 3.512
  },
  "pressure": {
    "relative": 30.023,
    "absolute": 27.351
  },
  "solar": {
    "uv": 0.0,
    "radiation": 0.01
  },
  "indoor": {
    "temperature": 79.5,
    "humidity": 67.0
  }
}