{
  "timestamp": "2026-01-24T01:30:00",
  "outdoor": {
    "temperature": 65.8,
    "feelsLike": 65.8,
    "dewPoint": 58.74,
    "humidity": 78.0
  },
  "wind": {
    "speed": 0.22,
    "gust": 1.12,
    "maxDailyGust": 11.41,
    "directionDeg": 62.0
  },
  "rain": {
    "hourly": 0.0,
    "daily": 0.0,
    "weekly": 0.0,
    "monthly": 0.039,
    "yearly": 12.791,
    "total": 12.791
  },
  "pressure": {
    "relative": 30.156,
    "absolute": 27.484
  },
  "solar": {
    "uv": 0.0,
    "radiation": 0.0
  },
  "indoor": {
    "temperature": 74.8,
    "humidity": 56.0
  }
}