{
  "timestamp": "2025-11-16T00:49:26.321000+05:30",
  "source": "ambientweather-backfill",
  "outdoor": {
    "temperature": 68.5,
    "feelsLike": 68.81,
    "dewPoint": 62.08,
    "humidity": 80.0
  },
  "wind": {
    "speed": 0.0,
    "gust": 0.0,
    "directionDeg": 79.0
  },
  "rain": {
    "hourly": 0.0,
    "daily": 0.0,
    "weekly": 0,
    "monthly": 0.0,
    "yearly": 12.642,
    "total": 12.642
  },
  "pressure": {
    "relative": 30.121,
    "absolute": 27.448
  },
  "solar": {
    "uv": 0.0,
    "radiation": 0.0
  }
}