{
  "timestamp": "2026-01-04T03:00:00",
  "outdoor": {
    "temperature": 64.4,
    "feelsLike": 64.4,
    "dewPoint": 56.66,
    "humidity": 76.0
  },
  "wind": {
    "speed": 0.45,
    "gust": 1.12,
    "maxDailyGust": 8.05,
    "directionDeg": 95.0
  },
  "rain": {
    "hourly": 0.0,
    "daily": 0.0,
    "weekly": 0.0,
    "monthly": 0.0,
    "yearly": 12.752,
    "total": 12.752
  },
  "pressure": {
    "relative": 30.115,
    "absolute": 27.442
  },
  "solar": {
    "uv": 0.0,
    "radiation": 0.0
  },
  "indoor": {
    "temperature": 75.7,
    "humidity": 58.0
  }
}